setup.py
fixedlist/__init__.py
fixedlist.egg-info/PKG-INFO
fixedlist.egg-info/SOURCES.txt
fixedlist.egg-info/dependency_links.txt
fixedlist.egg-info/not-zip-safe
fixedlist.egg-info/requires.txt
fixedlist.egg-info/top_level.txt