Metadata-Version: 1.1
Name: fixedlist
Version: 1.0
Summary: Fast performance fixed list for Redis
Home-page: http://www.amix.dk/
Author: amix
Author-email: amix@amix.dk
License: BSD
Keywords: redis fixed list small list short list
Platform: Any
Classifier: Development Status :: 5 - Production/Stable
Classifier: Intended Audience :: Developers
Classifier: License :: OSI Approved :: BSD License
Classifier: Operating System :: OS Independent
Classifier: Programming Language :: Python
Classifier: Topic :: Software Development :: Libraries :: Python Modules
